<weapon id="14">
	<name>LANCIARAZZI</name>
	<ammo>RR</ammo>
	<effects>
		<effect ref_id="1" name="">
			<cost/>
			<target>
				<type>PLAYER</type>
				<minNumber>1</minNumber>
				<maxNumber>1</maxNumber>
				<prevConstraints/>
			</target>
			<requirements>
				<requirement name="VISIBLE">TRUE</requirement>
				<requirement name="MIN_DISTANCE">1</requirement>
			</requirements>
			<actions>
				<action type="DAMAGE">
					<value>2</value>
				</action>
			</actions>
			<extras/>
		</effect>
		<effect ref_id="2" name="shift player">
			<cost/>
			<target>
				<type>PLAYER</type>
				<minNumber>1</minNumber>
				<maxNumber>1</maxNumber>
				<prevConstraints>
					<constraint>SAME</constraint>
				</prevConstraints>
			</target>
			<requirements>
				<requirement name="VISIBLE">TRUE</requirement>
				<requirement name="MIN_DISTANCE">1</requirement>
			</requirements>
			<actions>
				<action type="MOVE">
					<value>1</value>
				</action>
			</actions>
			<extras/>
		</effect>
		<effect ref_id="3" name="">
			<cost>B</cost>
			<target>
				<type>ME</type>
				<minNumber/>
				<maxNumber/>
				<prevConstraints/>
			</target>
			<requirements>
				<requirement name="IF_FIRST_CHECK_VISIBILITY_AFTER_SHIFT">TRUE</requirement>
				<requirement name="IF_FIRST_CHECK_IN_SQUARE_AFTER_SHIFT">FALSE</requirement>
			</requirements>
			<actions>
				<action type="MOVE">
					<value>2</value>
				</action>
			</actions>
			<extras/>
		</effect>
		<effect ref_id="4" name="">
			<cost>Y</cost>
			<target>
				<type>PLAYER</type>
				<minNumber>1</minNumber>
				<maxNumber>1</maxNumber>
				<prevConstraints>
					<constraint>SAME</constraint>
				</prevConstraints>
			</target>
			<requirements>
				<requirement name="VISIBLE">TRUE</requirement>
				<requirement name="MIN_DISTANCE">1</requirement>
			</requirements>
			<actions/>
			<extras>
				<extra name="DAMAGE_ALL_SQUARE">1</extra>
			</extras>
		</effect>
	</effects>
	<order>
		<sequence>
			<node>1</node>
		</sequence>
		<sequence>
			<node>1</node>
			<node>2</node>
		</sequence>
		<sequence>
			<node>1</node>
			<node>2</node>
			<node>3</node>
		</sequence>
		<sequence>
			<node>3</node>
			<node>1</node>
			<node>2</node>
		</sequence>
		<sequence>
			<node>1</node>
			<node>4</node>
			<node>2</node>
		</sequence>
		<sequence>
			<node>3</node>
			<node>1</node>
			<node>4</node>
			<node>2</node>
		</sequence>
		<sequence>
			<node>3</node>
			<node>1</node>
			<node>4</node>
		</sequence>
		<sequence>
			<node>1</node>
			<node>4</node>
			<node>2</node>
			<node>3</node>
		</sequence>
		<sequence>
			<node>1</node>
			<node>4</node>
			<node>3</node>
		</sequence>
	</order>
</weapon>